MANIFEST.in
setup.py
examples/humilis-microservice.yaml.j2
examples/layers/logging/outputs.yaml.j2
examples/layers/logging/resources.yaml.j2
examples/layers/storage/outputs.yaml.j2
examples/layers/storage/resources.yaml.j2
humilis/__init__.py
humilis/cli.py
humilis/config.py
humilis/environment.py
humilis/exceptions.py
humilis/j2.py
humilis/layer.py
humilis/reference.py
humilis/utils.py
humilis.egg-info/PKG-INFO
humilis.egg-info/SOURCES.txt
humilis.egg-info/dependency_links.txt
humilis.egg-info/entry_points.txt
humilis.egg-info/not-zip-safe
humilis.egg-info/requires.txt
humilis.egg-info/top_level.txt
tests/__init__.py