Metadata-Version: 1.1
Name: humilis
Version: 1.2.7
Summary: AWS cloudformation-based deployment framework
Home-page: http://github.com/humilis/humilis
Author: German Gomez-Herrero
Author-email: german@findhotel.net
License: MIT
Platform: UNKNOWN
Classifier: Programming Language :: Python :: 2
Classifier: Programming Language :: Python :: 3
